fpa_marcacoes/__init__.py
fpa_marcacoes/client.py
fpa_marcacoes/environment.py
fpa_marcacoes/auth/__init__.py
fpa_marcacoes/auth/client.py
fpa_marcacoes/core/__init__.py
fpa_marcacoes/core/api_error.py
fpa_marcacoes/core/pydantic_utilities.py
fpa_marcacoes/errors/__init__.py
fpa_marcacoes/errors/payment_needed_error.py
fpa_marcacoes/events/__init__.py
fpa_marcacoes/events/client.py
fpa_marcacoes/profile/__init__.py
fpa_marcacoes/profile/client.py
fpa_marcacoes/profile/types/__init__.py
fpa_marcacoes/profile/types/profile_get_response.py
fpa_marcacoes-0.1.1.dist-info/METADATA
fpa_marcacoes-0.1.1.dist-info/WHEEL
fpa_marcacoes-0.1.1.dist-info/top_level.txt
fpa_marcacoes-0.1.1.dist-info/RECORD
