Metadata-Version: 2.1
Name: fpa-marcacoes
Version: 0.1.1
Summary: An API Wrapper for the FPA's website of trainings and massage scheduler
Home-page: UNKNOWN
Author: André Oliveira
Author-email: andre_pinto_oliveira@outlook.pt
License: UNKNOWN
Keywords: python,FPA
Platform: UNKNOWN
Classifier: Development Status :: 3 - Alpha
Classifier: Intended Audience :: Education
Classifier: Programming Language :: Python :: 3
Classifier: Operating System :: MacOS :: MacOS X
Classifier: Operating System :: Microsoft :: Windows
Requires-Dist: Pillow
Requires-Dist: bs4
Requires-Dist: pydantic
Requires-Dist: requests
